[
  {
    "path": "/",
    "resourceSizes": [
      {
        "resourceType": "document",
        "budget": 12.9
      },
      {
        "resourceType": "script",
        "budget": 65.2
      },
      {
        "resourceType": "stylesheet",
        "budget": 0.3
      },
      {
        "resourceType": "other",
        "budget": 27.8
      }
    ],
    "resourceCounts": [
      {
        "resourceType": "third-party",
        "budget": 1
      },
      {
        "resourceType": "stylesheet",
        "budget": 1
      },
      {
        "resourceType": "script",
        "budget": 2
      },
      {
        "resourceType": "font",
        "budget": 3
      }
    ]
  }
]
